lidbox/__init__.py
lidbox/__main__.py
lidbox/api.py
lidbox/cli.py
lidbox/metrics.py
lidbox/system.py
lidbox/visualization.py
lidbox/dataset/__init__.py
lidbox/dataset/pipelines.py
lidbox/dataset/steps.py
lidbox/dataset/tf_utils.py
lidbox/embeddings/__init__.py
lidbox/embeddings/sklearn_utils.py
lidbox/features/__init__.py
lidbox/features/audio.py
lidbox/models/__init__.py
lidbox/models/ap_lstm.py
lidbox/models/bi_gru.py
lidbox/models/clstm.py
lidbox/models/cnn.py
lidbox/models/convnet_extractor.py
lidbox/models/crnn.py
lidbox/models/dnn.py
lidbox/models/keras_utils.py
lidbox/models/lstm.py
lidbox/models/multilevel_attention.py
lidbox/models/spherespeaker.py
lidbox/models/xvector.py
lidbox/models/xvector_2d.py
lidbox/models/xvector_2d_skip.py
lidbox/models/xvector_2d_v2.py
lidbox/models/xvector_2d_v3.py
lidbox/models/xvector_classlayers.py
lidbox/models/xvector_extended.py
lidbox/models/xvector_freq_attention.py
lidbox/models/xvector_mobilenet.py
lidbox/models/xvector_resnet.py
lidbox/models/xvector_tfjs.py
lidbox/schemas/__init__.py
lidbox/schemas/config.yaml
lidbox/schemas/definitions.yaml
lidbox-0.7.1.dist-info/LICENSE
lidbox-0.7.1.dist-info/METADATA
lidbox-0.7.1.dist-info/WHEEL
lidbox-0.7.1.dist-info/entry_points.txt
lidbox-0.7.1.dist-info/top_level.txt
lidbox-0.7.1.dist-info/RECORD
