Metadata-Version: 2.1
Name: lidbox
Version: 0.7.1
Summary: End-to-end spoken language identification (LID) on TensorFlow
Home-page: https://github.com/matiaslindgren/lidbox
Author: Matias Lindgren
Author-email: matias.lindgren@iki.fi
License: MIT
Platform: UNKNOWN
Classifier: Programming Language :: Python :: 3
Classifier: License :: OSI Approved :: MIT License
Requires-Python: >= 3.7.*
Requires-Dist: PyYAML (~=5.1)
Requires-Dist: colorcet (~=2.0.2)
Requires-Dist: jsonschema
Requires-Dist: kaldiio (~=2.13)
Requires-Dist: matplotlib (~=3.1)
Requires-Dist: scikit-learn (~=0.22.2)
Requires-Dist: webrtcvad (~=2.0.10)
Requires-Dist: miniaudio (~=1.37)
